{
  "$schema": "https://mintlify.com/schema.json",
  "name": "turntable",
  "favicon": "/favicon.svg",
  "colors": {
    "primary": "#6C757D",
    "light": "#E5E5E5",
    "dark": "#0D9373",
    "anchors": {
      "from": "#6C757D",
      "to": "#ADB5BD"
    }
  },
  "navigation": [
    {
      "group": "Welcome to Turntable",
      "pages": [
        "introduction",
        "quickstart"
      ]
    },
    {
      "group": "Vinyl Essentials",
      "pages": [
        "essentials/markdown",
        "essentials/code",
        "essentials/images",
        "essentials/settings",
        "essentials/navigation",
        "essentials/reusable-snippets"
      ]
    }
  ],
  "footerSocials": {
    "twitter": "https://twitter.com/mintlify",
    "github": "https://github.com/mintlify",
    "linkedin": "https://www.linkedin.com/company/mintsearch"
  }
}